sorted_list.py
sorted_list-1.0.0.dist-info/LICENSE
sorted_list-1.0.0.dist-info/METADATA
sorted_list-1.0.0.dist-info/WHEEL
sorted_list-1.0.0.dist-info/top_level.txt
sorted_list-1.0.0.dist-info/RECORD
