Metadata-Version: 2.1
Name: sorted-list
Version: 1.0.0
Summary: A sorted list for Python.
Home-page: https://github.com/megacodist/sorted-list/tree/main
Author: Megacodist
Author-email: megacodist@gmail.com
Keywords: list,sorted list
Classifier: Programming Language :: Python :: 3
Classifier: License :: OSI Approved :: MIT License
Classifier: Operating System :: OS Independent
Requires-Python: >=3.10
License-File: LICENSE
